{
  "type": "preflow",
  "path": "/Users/fanzhang/Documents/github/webauto/workflows/1688/analysis/1688-page-structure-analysis.json#anchor",
  "name": "1688页面结构分析 Anchor Check",
  "startedAt": 1761202917372,
  "finishedAt": 1761202917372,
  "success": true,
  "error": null,
  "variables": {
    "workflowName": "1688页面结构分析 Anchor Check",
    "sessionId": "sess-1761202905989-778015",
    "sessionDir": "/Users/fanzhang/.webauto/sessions/sess-1761202905989-778015",
    "debug": false,
    "startTime": "2025-10-23T07:01:57.136Z",
    "workflowStarted": true,
    "sessionAttached": true,
    "anchorSettled.default": true,
    "anchorSelector.default": ".userAvatarLogo img",
    "anchorRect.default": {
      "x": 448,
      "y": 0,
      "width": 1024,
      "height": 52
    },
    "anchorSettled": true,
    "anchorSelector": ".userAvatarLogo img",
    "anchorRect": {
      "x": 448,
      "y": 0,
      "width": 1024,
      "height": 52
    },
    "anchorSettled_default": true,
    "anchorSelector_default": ".userAvatarLogo img",
    "anchorRect_default": {
      "x": 448,
      "y": 0,
      "width": 1024,
      "height": 52
    },
    "endTime": "2025-10-23T07:01:57.372Z",
    "sessionPersisted": true,
    "workflowCompleted": true,
    "executionTime": 235
  },
  "outputs": {},
  "parameters": {
    "debug": false,
    "sessionId": "sess-1761202905989-778015"
  },
  "preflows": []
}