{
  "type": "preflow",
  "path": "/Users/fanzhang/Documents/github/webauto/workflows/preflows/1688-login-preflow.json",
  "name": "1688 Login Preflow",
  "startedAt": 1760492806057,
  "finishedAt": 1760492806057,
  "success": true,
  "error": null,
  "variables": {
    "workflowName": "1688 Login Preflow",
    "sessionId": "sess-1760492799148-648402",
    "sessionDir": "/Users/fanzhang/.webauto/sessions/sess-1760492799148-648402",
    "debug": true,
    "startTime": "2025-10-15T01:46:39.149Z",
    "workflowStarted": true,
    "browserInitialized": true,
    "browserInfo": {
      "headless": false,
      "viewport": {
        "width": 1280,
        "height": 900
      }
    },
    "lastWaitMs": 1806,
    "cookiesLoaded": true,
    "cookieCount": 90,
    "cookiePath": "/Users/fanzhang/.webauto/cookies/1688-domestic.json",
    "currentUrl": "https://www.1688.com/",
    "navigationCompleted": true,
    "lastNavigationTime": "2025-10-15T01:46:43.424Z",
    "antiBotWaitMs": 1011,
    "modalsDismissed": 0,
    "isLoggedIn": true,
    "loginInfo": {
      "cookieHit": true
    },
    "loginVerifiedAt": "2025-10-15T01:46:46.054Z",
    "cookieSaved": true,
    "cookieSavePath": "/Users/fanzhang/.webauto/cookies/1688-domestic.json",
    "cookieSaveCount": 90,
    "resultSaved": true,
    "resultFilePath": "workflows/records/preflow-1688-login-success-2025-10-15T01-46-46-056Z.json",
    "resultFilename": "preflow-1688-login-success-2025-10-15T01-46-46-056Z.json",
    "handshakeSignalPath": "/Users/fanzhang/.webauto/sessions/sess-1760492799148-648402/login.json",
    "behaviorLogPath": "/Users/fanzhang/.webauto/sessions/sess-1760492799148-648402/behavior-1688 Login Preflow-2025-10-15T01-46-46-056Z.json",
    "behaviorEventCount": 110,
    "contextExportPath": "/Users/fanzhang/.webauto/sessions/sess-1760492799148-648402/context.json",
    "endTime": "2025-10-15T01:46:46.057Z",
    "sessionPersisted": true,
    "logsExported": true,
    "workflowCompleted": true,
    "executionTime": 6908
  },
  "outputs": {},
  "parameters": {
    "debug": true,
    "sessionId": "sess-1760492799148-648402"
  },
  "preflows": []
}