{
  "type": "preflow",
  "path": "/Users/fanzhang/Documents/github/webauto/workflows/preflows/1688-login-preflow.json",
  "name": "1688 Login Preflow",
  "startedAt": 1760599310865,
  "finishedAt": 1760599310865,
  "success": true,
  "error": null,
  "variables": {
    "workflowName": "1688 Login Preflow",
    "sessionId": "sess-1760599299864-707071",
    "sessionDir": "/Users/fanzhang/.webauto/sessions/sess-1760599299864-707071",
    "debug": true,
    "startTime": "2025-10-16T07:21:39.866Z",
    "workflowStarted": true,
    "browserInitialized": true,
    "browserInfo": {
      "headless": false,
      "viewport": {
        "width": 1920,
        "height": 1080
      }
    },
    "lastWaitMs": 2940,
    "cookiesLoaded": true,
    "cookieCount": 176,
    "cookiePath": "/Users/fanzhang/.webauto/cookies/1688-domestic.json",
    "currentUrl": "https://www.1688.com/",
    "navigationCompleted": true,
    "lastNavigationTime": "2025-10-16T07:21:47.495Z",
    "antiBotWaitMs": 1858,
    "modalsDismissed": 0,
    "isLoggedIn": true,
    "loginInfo": {
      "cookieHit": true
    },
    "loginVerifiedAt": "2025-10-16T07:21:50.844Z",
    "cookieSaved": true,
    "cookieSavePath": "/Users/fanzhang/.webauto/cookies/1688-domestic.json",
    "cookieSaveCount": 176,
    "resultSaved": true,
    "resultFilePath": "workflows/records/preflow-1688-login-success-2025-10-16T07-21-50-850Z.json",
    "resultFilename": "preflow-1688-login-success-2025-10-16T07-21-50-850Z.json",
    "handshakeSignalPath": "/Users/fanzhang/.webauto/sessions/sess-1760599299864-707071/login.json",
    "behaviorLogPath": "/Users/fanzhang/.webauto/sessions/sess-1760599299864-707071/behavior-1688 Login Preflow-2025-10-16T07-21-50-858Z.json",
    "behaviorEventCount": 345,
    "contextExportPath": "/Users/fanzhang/.webauto/sessions/sess-1760599299864-707071/context.json",
    "endTime": "2025-10-16T07:21:50.865Z",
    "sessionPersisted": true,
    "logsExported": true,
    "workflowCompleted": true,
    "executionTime": 10999
  },
  "outputs": {},
  "parameters": {
    "debug": true,
    "sessionId": "sess-1760599299864-707071"
  },
  "preflows": []
}