{
  "timestamp": "2025-10-17T11-15-22-239Z",
  "workflowType": "homepage",
  "success": true,
  "executionTime": 0,
  "metadata": {
    "workflowType": "homepage",
    "capturedAt": "2025-10-17T11:15:22.240Z",
    "linkCount": 0,
    "pageCount": 0,
    "scrollCount": 0
  },
  "results": {},
  "variables": {
    "workflowName": "1688 Login Preflow",
    "sessionId": "sess-1760699710244-696188",
    "sessionDir": "/Users/fanzhang/.webauto/sessions/sess-1760699710244-696188",
    "debug": true,
    "startTime": "2025-10-17T11:15:10.246Z",
    "workflowStarted": true,
    "browserInitialized": true,
    "browserInfo": {
      "headless": false,
      "viewport": {
        "width": 1920,
        "height": 1080
      }
    },
    "lastWaitMs": 2685,
    "cookiesLoaded": true,
    "cookieCount": 171,
    "cookiePath": "/Users/fanzhang/.webauto/cookies/1688-domestic.json",
    "currentUrl": "https://www.1688.com/",
    "navigationCompleted": true,
    "lastNavigationTime": "2025-10-17T11:15:18.951Z",
    "antiBotWaitMs": 1866,
    "modalsDismissed": 0,
    "isLoggedIn": true,
    "loginInfo": {
      "cookieHit": true
    },
    "loginVerifiedAt": "2025-10-17T11:15:22.237Z",
    "cookieSaved": true,
    "cookieSavePath": "/Users/fanzhang/.webauto/cookies/1688-domestic.json",
    "cookieSaveCount": 171
  }
}